junoplatform/__init__.py
junoplatform/api/__init__.py
junoplatform/api/cloud.py
junoplatform/api/local.py
junoplatform/io/__init__.py
junoplatform/io/_driver.py
junoplatform/io/data_clean.py
junoplatform/io/dealer.py
junoplatform/io/misc.py
junoplatform/io/utils.py
junoplatform/log/__init__.py
junoplatform/meta/__init__.py
junoplatform/meta/decorators.py
junoplatform/templates/config.json
junoplatform/templates/main.py
junoplatform/tools/__init__.py
junoplatform/tools/cmd.py
junoplatform-1.4.5.dist-info/entry_points.txt
junoplatform-1.4.5.dist-info/WHEEL
junoplatform-1.4.5.dist-info/METADATA
junoplatform-1.4.5.dist-info/RECORD
