Metadata-Version: 2.1
Name: junoplatform
Version: 1.4.5
Summary: juno AI platform lib
Author-email: "Bruce.Lu" <lzbgt@icloud.com>
Requires-Python: >=3.10
Classifier: Programming Language :: Python :: 3
Classifier: License :: OSI Approved :: MIT License
Classifier: Operating System :: OS Independent
Requires-Dist: flit_core >=3.9.0
Requires-Dist: requests
Requires-Dist: pulsar-client
Requires-Dist: numpy
Requires-Dist: python-decouple
Requires-Dist: pyyaml
Requires-Dist: clickhouse-connect
Requires-Dist: pymongo
Requires-Dist: questdb
Requires-Dist: postgres
Requires-Dist: cryptography
Requires-Dist: bcrypt
Requires-Dist: redis
Requires-Dist: pylint
Requires-Dist: elasticsearch
Requires-Dist: dateparser
Requires-Dist: pydantic>=1.10.12
Requires-Dist: oss2
Requires-Dist: click
Requires-Dist: findimports
Requires-Dist: pyzmq
Requires-Dist: pycryptodome
Project-URL: Bug Tracker, https://github.com/lzbgt/sampleproject/issues
Project-URL: Homepage, https://github.com/lzbgt/sampleproject
